README.md
setup.py
xict/__init__.py
xict.egg-info/PKG-INFO
xict.egg-info/SOURCES.txt
xict.egg-info/dependency_links.txt
xict.egg-info/top_level.txt