Metadata-Version: 1.1
Name: xict
Version: 0.0.0
Summary: xict
Home-page: http://github.com/serwy/xict
Author: Roger D. Serwy
Author-email: roger.serwy@gmail.com
License: UNKNOWN
Platform: UNKNOWN
Classifier: Development Status :: 2 - Pre-Alpha
Classifier: Operating System :: OS Independent
Classifier: Programming Language :: Python :: 3
